jaeger_lab_to_nwb/__init__.py
jaeger_lab_to_nwb/cmd_line.py
jaeger_lab_to_nwb/conversion_module.py
jaeger_lab_to_nwb/bpodconverter/__init__.py
jaeger_lab_to_nwb/bpodconverter/bpodconverter.py
jaeger_lab_to_nwb/bpodconverter/bpoddatainterface.py
jaeger_lab_to_nwb/bpodconverter/metafile.yml
jaeger_lab_to_nwb/fretconverter/__init__.py
jaeger_lab_to_nwb/fretconverter/fretconverter.py
jaeger_lab_to_nwb/fretconverter/fretdatainterface.py
jaeger_lab_to_nwb/labviewconverter/__init__.py
jaeger_lab_to_nwb/labviewconverter/labviewconverter.py
jaeger_lab_to_nwb/labviewconverter/labviewdatainterface.py
jaeger_lab_to_nwb/resources/__init__.py
jaeger_lab_to_nwb/resources/load_intan/__init__.py
jaeger_lab_to_nwb/resources/load_intan/data_to_result.py
jaeger_lab_to_nwb/resources/load_intan/get_bytes_per_data_block.py
jaeger_lab_to_nwb/resources/load_intan/load_intan.py
jaeger_lab_to_nwb/resources/load_intan/notch_filter.py
jaeger_lab_to_nwb/resources/load_intan/qstring.py
jaeger_lab_to_nwb/resources/load_intan/read_header.py
jaeger_lab_to_nwb/resources/load_intan/read_one_data_block.py
jaeger_lab_to_nwb/treadmillconverter/__init__.py
jaeger_lab_to_nwb/treadmillconverter/intandatainterface.py
jaeger_lab_to_nwb/treadmillconverter/treadmillconverter.py
jaeger_lab_to_nwb/treadmillconverter/treadmilldatainterface.py
jaeger_lab_to_nwb-0.1.1.dist-info/LICENSE
jaeger_lab_to_nwb-0.1.1.dist-info/METADATA
jaeger_lab_to_nwb-0.1.1.dist-info/WHEEL
jaeger_lab_to_nwb-0.1.1.dist-info/entry_points.txt
jaeger_lab_to_nwb-0.1.1.dist-info/top_level.txt
jaeger_lab_to_nwb-0.1.1.dist-info/RECORD
