Metadata-Version: 2.1
Name: jaeger-lab-to-nwb
Version: 0.1.1
Summary: NWB conversion scripts and tutorials.
Home-page: UNKNOWN
Author: Luiz Tauffer and Ben Dichter
License: UNKNOWN
Platform: UNKNOWN
License-File: LICENSE
Requires-Dist: nwb-conversion-tools (==0.6.3)
Requires-Dist: ndx-fret (==0.2.1)
Requires-Dist: ndx-events (==0.2.0)
Requires-Dist: pyintan (==0.3.0)
Requires-Dist: nwbwidgets (==0.8.0)
Requires-Dist: pynwb (==2.0.1)
Requires-Dist: h5py (==3.6.0)
Requires-Dist: hdmf (==3.2.1)
Requires-Dist: jupyterlab (==3.3.2)
